gwop/__init__.py
gwop/definitions.py
gwop/gwop.py
gwop-1.0.1.dist-info/entry_points.txt
gwop-1.0.1.dist-info/WHEEL
gwop-1.0.1.dist-info/METADATA
gwop-1.0.1.dist-info/RECORD
